README.md
setup.cfg
setup.py
netbox_data/__init__.py
netbox_data/filtersets.py
netbox_data/forms.py
netbox_data/graphql.py
netbox_data/models.py
netbox_data/navigation.py
netbox_data/search.py
netbox_data/tables.py
netbox_data/urls.py
netbox_data/utilities.py
netbox_data/views.py
netbox_data.egg-info/PKG-INFO
netbox_data.egg-info/SOURCES.txt
netbox_data.egg-info/dependency_links.txt
netbox_data.egg-info/not-zip-safe
netbox_data.egg-info/top_level.txt
netbox_data/api/__init__.py
netbox_data/api/serializers.py
netbox_data/api/urls.py
netbox_data/api/views.py
netbox_data/migrations/0001_initial.py
netbox_data/migrations/__init__.py