Metadata-Version: 2.1
Name: netbox_data
Version: 1.1.0
Summary: A Netbox Data plugin
